{
  "control_mode": "host",
  "controller_algorithm": "predictive",
  "controller_state": "host",
  "fault_samples": 0,
  "heater": "heater_bed",
  "initial_temperature_c": 51.92,
  "maximum_temperature_c": 75.24,
  "overshoot_c": 0.23999999999999488,
  "qualification_duration_s": 111.7361695130021,
  "ready_band_c": 1.0,
  "ready_hold_s": 60.0,
  "environment": "printer open",
  "host_promotion_status": "accepted",
  "source_csv": "host-predictive-bed75-open-blend-20260720.csv",
  "target_to_ambient_delta_c": 46.91,
  "steady_power_delta_rms": 0.0015201737543607808,
  "steady_power_mean": 0.6488839790989233,
  "steady_power_stddev": 0.013909243335548887,
  "steady_samples": 121,
  "steady_temperature_error_rms_c": 0.319711905438849,
  "steady_temperature_mean_c": 74.78322314049588,
  "steady_temperature_peak_error_c": 0.9000000000000057,
  "steady_temperature_stddev_c": 0.2349967992608939,
  "target_c": 75.0,
  "thermal_control_band_c": 1.0,
  "thermal_model_delay_s": 2.0,
  "thermal_model_gain": 80.0,
  "thermal_model_horizon_s": 30.0,
  "thermal_model_source": "base",
  "thermal_model_tau_s": 150.0,
  "time_to_first_crossing_s": 99.71110937699996,
  "time_to_print_s": 51.61501981699985
}
